xmind_to_markdown/__init__.py
xmind_to_markdown/md_converter.py
xmind_to_markdown/server.py
xmind_to_markdown/xmind_parser.py
xmind_to_markdown_mcp-0.1.3.dist-info/METADATA
xmind_to_markdown_mcp-0.1.3.dist-info/WHEEL
xmind_to_markdown_mcp-0.1.3.dist-info/entry_points.txt
xmind_to_markdown_mcp-0.1.3.dist-info/licenses/LICENSE
xmind_to_markdown_mcp-0.1.3.dist-info/RECORD
