Metadata-Version: 2.4
Name: xmind-to-markdown-mcp
Version: 0.1.3
Summary: MCP Server for converting XMind files to Markdown format
Project-URL: Homepage, https://github.com/jiandong0718/mcp-xmind-to-markdown
Project-URL: Repository, https://github.com/jiandong0718/mcp-xmind-to-markdown
Project-URL: Issues, https://github.com/jiandong0718/mcp-xmind-to-markdown/issues
Project-URL: Documentation, https://github.com/jiandong0718/mcp-xmind-to-markdown#readme
Author-email: "jiandong.liu" <jiandong.yh@gmail.com>
License: MIT
License-File: LICENSE
Keywords: ai,converter,llm,markdown,mcp,xmind
Classifier: Development Status :: 4 - Beta
Classifier: Intended Audience :: Developers
Classifier: License :: OSI Approved :: MIT License
Classifier: Programming Language :: Python :: 3
Classifier: Programming Language :: Python :: 3.10
Classifier: Programming Language :: Python :: 3.11
Classifier: Programming Language :: Python :: 3.12
Classifier: Programming Language :: Python :: 3.13
Classifier: Topic :: Software Development :: Libraries :: Python Modules
Classifier: Topic :: Text Processing :: Markup :: Markdown
Requires-Python: >=3.10
Requires-Dist: fastmcp>=2.0.0
Requires-Dist: xmindparser>=1.0.9
Provides-Extra: dev
Requires-Dist: black>=23.0.0; extra == 'dev'
Requires-Dist: pytest-cov>=4.0.0; extra == 'dev'
Requires-Dist: pytest>=7.0.0; extra == 'dev'
Requires-Dist: ruff>=0.1.0; extra == 'dev'
